pygit2-stubs/METADATA.toml
pygit2-stubs/__init__.pyi
pygit2-stubs/_build.pyi
pygit2-stubs/_libgit2.pyi
pygit2-stubs/_pygit2.pyi
pygit2-stubs/_run.pyi
pygit2-stubs/blame.pyi
pygit2-stubs/blob.pyi
pygit2-stubs/branches.pyi
pygit2-stubs/callbacks.pyi
pygit2-stubs/config.pyi
pygit2-stubs/credentials.pyi
pygit2-stubs/enums.pyi
pygit2-stubs/errors.pyi
pygit2-stubs/ffi.pyi
pygit2-stubs/filter.pyi
pygit2-stubs/index.pyi
pygit2-stubs/legacyenums.pyi
pygit2-stubs/packbuilder.pyi
pygit2-stubs/py.typed
pygit2-stubs/references.pyi
pygit2-stubs/refspec.pyi
pygit2-stubs/remotes.pyi
pygit2-stubs/repository.pyi
pygit2-stubs/settings.pyi
pygit2-stubs/submodules.pyi
pygit2-stubs/utils.pyi
types_pygit2-1.15.0.20250319.dist-info/LICENSE
types_pygit2-1.15.0.20250319.dist-info/METADATA
types_pygit2-1.15.0.20250319.dist-info/WHEEL
types_pygit2-1.15.0.20250319.dist-info/top_level.txt
types_pygit2-1.15.0.20250319.dist-info/RECORD
